pafpy/__init__.py
pafpy/__version__.py
pafpy/paffile.py
pafpy/pafrecord.py
pafpy/strand.py
pafpy/tag.py
pafpy/utils.py
pafpy-0.2.0.dist-info/LICENSE
pafpy-0.2.0.dist-info/WHEEL
pafpy-0.2.0.dist-info/METADATA
pafpy-0.2.0.dist-info/RECORD
