Metadata-Version: 2.1
Name: pafpy
Version: 0.2.0
Summary: A lightweight library for working with PAF (Pairwise mApping Format) files
Home-page: https://github.com/mbhall88/pafpy
License: Unlicense
Keywords: paf,python,bioinformatics,library,alignment
Author: Michael Hall
Author-email: michael@mbh.sh
Maintainer: Michael Hall
Maintainer-email: michael@mbh.sh
Requires-Python: >=3.6,<4.0
Classifier: Intended Audience :: Science/Research
Classifier: License :: Other/Proprietary License
Classifier: Programming Language :: Python :: 3
Classifier: Programming Language :: Python :: 3 :: Only
Classifier: Programming Language :: Python :: 3.6
Classifier: Programming Language :: Python :: 3.7
Classifier: Programming Language :: Python :: 3.8
Classifier: Programming Language :: Python :: 3.9
Classifier: Topic :: Scientific/Engineering :: Bio-Informatics
Classifier: Topic :: Software Development :: Libraries
Project-URL: Documentation, https://pafpy.xyz
Project-URL: Repository, https://github.com/mbhall88/pafpy
